[
  {
    "requestId": "1763813926655_UYuryiUyrWbLZyv4AAAC",
    "timestamp": 1763813926655,
    "status": "failed",
    "memoryUsed": 1392,
    "duration": 26
  },
  {
    "requestId": "1763813927153_UYuryiUyrWbLZyv4AAAC",
    "timestamp": 1763813927153,
    "status": "failed",
    "memoryUsed": 1392,
    "duration": 18
  },
  {
    "requestId": "1763813927648_UYuryiUyrWbLZyv4AAAC",
    "timestamp": 1763813927648,
    "status": "failed",
    "memoryUsed": 11752,
    "duration": 9
  },
  {
    "requestId": "1763813928147_UYuryiUyrWbLZyv4AAAC",
    "timestamp": 1763813928147,
    "status": "failed",
    "memoryUsed": 12084,
    "duration": 5
  },
  {
    "requestId": "1763813928654_UYuryiUyrWbLZyv4AAAC",
    "timestamp": 1763813928654,
    "status": "failed",
    "memoryUsed": 10996,
    "duration": 6
  },
  {
    "requestId": "1763813929148_UYuryiUyrWbLZyv4AAAC",
    "timestamp": 1763813929148,
    "status": "failed",
    "memoryUsed": 11680,
    "duration": 7
  },
  {
    "requestId": "1763813929651_UYuryiUyrWbLZyv4AAAC",
    "timestamp": 1763813929651,
    "status": "failed",
    "memoryUsed": 11080,
    "duration": 7
  },
  {
    "requestId": "1763813930148_UYuryiUyrWbLZyv4AAAC",
    "timestamp": 1763813930148,
    "status": "failed",
    "memoryUsed": 11608,
    "duration": 17
  },
  {
    "requestId": "1763813930651_UYuryiUyrWbLZyv4AAAC",
    "timestamp": 1763813930651,
    "status": "failed",
    "memoryUsed": 13304,
    "duration": 5
  },
  {
    "requestId": "1763813931153_UYuryiUyrWbLZyv4AAAC",
    "timestamp": 1763813931153,
    "status": "failed",
    "memoryUsed": 13988,
    "duration": 7
  }
]