[
  {
    "timestamp": "2025-11-23T10:43:06.200Z",
    "level": "info",
    "message": "요청 시작",
    "clientId": "lzua0UoqqZIyEBz4AAAC",
    "requestId": "1763894586200_lzua0UoqqZIyEBz4AAAC",
    "details": {
      "imageSize": 1392
    }
  },
  {
    "timestamp": "2025-11-23T10:43:06.433Z",
    "level": "info",
    "message": "검증 실패",
    "clientId": "lzua0UoqqZIyEBz4AAAC",
    "requestId": "1763894586200_lzua0UoqqZIyEBz4AAAC",
    "details": {
      "verificationResult": [
        1,
        0,
        0,
        0,
        0
      ],
      "isSuccess": false,
      "duration": 233
    }
  },
  {
    "timestamp": "2025-11-23T10:43:06.690Z",
    "level": "info",
    "message": "요청 시작",
    "clientId": "lzua0UoqqZIyEBz4AAAC",
    "requestId": "1763894586690_lzua0UoqqZIyEBz4AAAC",
    "details": {
      "imageSize": 1392
    }
  },
  {
    "timestamp": "2025-11-23T10:43:06.773Z",
    "level": "info",
    "message": "검증 실패",
    "clientId": "lzua0UoqqZIyEBz4AAAC",
    "requestId": "1763894586690_lzua0UoqqZIyEBz4AAAC",
    "details": {
      "verificationResult": [
        1,
        0,
        0,
        0,
        0
      ],
      "isSuccess": false,
      "duration": 83
    }
  },
  {
    "timestamp": "2025-11-23T10:43:07.192Z",
    "level": "info",
    "message": "요청 시작",
    "clientId": "lzua0UoqqZIyEBz4AAAC",
    "requestId": "1763894587191_lzua0UoqqZIyEBz4AAAC",
    "details": {
      "imageSize": 11268
    }
  },
  {
    "timestamp": "2025-11-23T10:43:07.294Z",
    "level": "info",
    "message": "검증 실패",
    "clientId": "lzua0UoqqZIyEBz4AAAC",
    "requestId": "1763894587191_lzua0UoqqZIyEBz4AAAC",
    "details": {
      "verificationResult": [
        1,
        1,
        0,
        1,
        1
      ],
      "isSuccess": false,
      "duration": 103
    }
  },
  {
    "timestamp": "2025-11-23T10:43:07.691Z",
    "level": "info",
    "message": "요청 시작",
    "clientId": "lzua0UoqqZIyEBz4AAAC",
    "requestId": "1763894587691_lzua0UoqqZIyEBz4AAAC",
    "details": {
      "imageSize": 11364
    }
  },
  {
    "timestamp": "2025-11-23T10:43:07.781Z",
    "level": "info",
    "message": "검증 실패",
    "clientId": "lzua0UoqqZIyEBz4AAAC",
    "requestId": "1763894587691_lzua0UoqqZIyEBz4AAAC",
    "details": {
      "verificationResult": [
        0,
        1,
        0,
        1,
        1
      ],
      "isSuccess": false,
      "duration": 90
    }
  },
  {
    "timestamp": "2025-11-23T10:43:08.191Z",
    "level": "info",
    "message": "요청 시작",
    "clientId": "lzua0UoqqZIyEBz4AAAC",
    "requestId": "1763894588191_lzua0UoqqZIyEBz4AAAC",
    "details": {
      "imageSize": 10620
    }
  },
  {
    "timestamp": "2025-11-23T10:43:08.272Z",
    "level": "info",
    "message": "검증 성공",
    "clientId": "lzua0UoqqZIyEBz4AAAC",
    "requestId": "1763894588191_lzua0UoqqZIyEBz4AAAC",
    "details": {
      "verificationResult": [
        1,
        1,
        1,
        1,
        1
      ],
      "isSuccess": true,
      "duration": 81
    }
  },
  {
    "timestamp": "2025-11-23T10:43:08.688Z",
    "level": "info",
    "message": "요청 시작",
    "clientId": "lzua0UoqqZIyEBz4AAAC",
    "requestId": "1763894588688_lzua0UoqqZIyEBz4AAAC",
    "details": {
      "imageSize": 12476
    }
  },
  {
    "timestamp": "2025-11-23T10:43:08.766Z",
    "level": "info",
    "message": "검증 실패",
    "clientId": "lzua0UoqqZIyEBz4AAAC",
    "requestId": "1763894588688_lzua0UoqqZIyEBz4AAAC",
    "details": {
      "verificationResult": [
        1,
        1,
        0,
        0,
        1
      ],
      "isSuccess": false,
      "duration": 78
    }
  },
  {
    "timestamp": "2025-11-23T10:43:09.192Z",
    "level": "info",
    "message": "요청 시작",
    "clientId": "lzua0UoqqZIyEBz4AAAC",
    "requestId": "1763894589192_lzua0UoqqZIyEBz4AAAC",
    "details": {
      "imageSize": 11108
    }
  },
  {
    "timestamp": "2025-11-23T10:43:09.270Z",
    "level": "info",
    "message": "검증 실패",
    "clientId": "lzua0UoqqZIyEBz4AAAC",
    "requestId": "1763894589192_lzua0UoqqZIyEBz4AAAC",
    "details": {
      "verificationResult": [
        1,
        1,
        0,
        0,
        1
      ],
      "isSuccess": false,
      "duration": 78
    }
  },
  {
    "timestamp": "2025-11-23T10:43:09.686Z",
    "level": "info",
    "message": "요청 시작",
    "clientId": "lzua0UoqqZIyEBz4AAAC",
    "requestId": "1763894589686_lzua0UoqqZIyEBz4AAAC",
    "details": {
      "imageSize": 12920
    }
  },
  {
    "timestamp": "2025-11-23T10:43:09.764Z",
    "level": "info",
    "message": "검증 실패",
    "clientId": "lzua0UoqqZIyEBz4AAAC",
    "requestId": "1763894589686_lzua0UoqqZIyEBz4AAAC",
    "details": {
      "verificationResult": [
        1,
        1,
        0,
        1,
        1
      ],
      "isSuccess": false,
      "duration": 77
    }
  },
  {
    "timestamp": "2025-11-23T10:43:10.191Z",
    "level": "info",
    "message": "요청 시작",
    "clientId": "lzua0UoqqZIyEBz4AAAC",
    "requestId": "1763894590191_lzua0UoqqZIyEBz4AAAC",
    "details": {
      "imageSize": 12592
    }
  },
  {
    "timestamp": "2025-11-23T10:43:10.266Z",
    "level": "info",
    "message": "검증 성공",
    "clientId": "lzua0UoqqZIyEBz4AAAC",
    "requestId": "1763894590191_lzua0UoqqZIyEBz4AAAC",
    "details": {
      "verificationResult": [
        1,
        1,
        1,
        1,
        1
      ],
      "isSuccess": true,
      "duration": 75
    }
  },
  {
    "timestamp": "2025-11-23T10:43:10.689Z",
    "level": "info",
    "message": "요청 시작",
    "clientId": "lzua0UoqqZIyEBz4AAAC",
    "requestId": "1763894590689_lzua0UoqqZIyEBz4AAAC",
    "details": {
      "imageSize": 12368
    }
  },
  {
    "timestamp": "2025-11-23T10:43:10.769Z",
    "level": "info",
    "message": "검증 성공",
    "clientId": "lzua0UoqqZIyEBz4AAAC",
    "requestId": "1763894590689_lzua0UoqqZIyEBz4AAAC",
    "details": {
      "verificationResult": [
        1,
        1,
        1,
        1,
        1
      ],
      "isSuccess": true,
      "duration": 80
    }
  },
  {
    "timestamp": "2025-11-23T10:43:11.192Z",
    "level": "info",
    "message": "요청 시작",
    "clientId": "lzua0UoqqZIyEBz4AAAC",
    "requestId": "1763894591192_lzua0UoqqZIyEBz4AAAC",
    "details": {
      "imageSize": 13280
    }
  },
  {
    "timestamp": "2025-11-23T10:43:11.270Z",
    "level": "info",
    "message": "검증 성공",
    "clientId": "lzua0UoqqZIyEBz4AAAC",
    "requestId": "1763894591192_lzua0UoqqZIyEBz4AAAC",
    "details": {
      "verificationResult": [
        1,
        1,
        1,
        1,
        1
      ],
      "isSuccess": true,
      "duration": 78
    }
  },
  {
    "timestamp": "2025-11-23T10:43:11.687Z",
    "level": "info",
    "message": "요청 시작",
    "clientId": "lzua0UoqqZIyEBz4AAAC",
    "requestId": "1763894591687_lzua0UoqqZIyEBz4AAAC",
    "details": {
      "imageSize": 13560
    }
  },
  {
    "timestamp": "2025-11-23T10:43:11.766Z",
    "level": "info",
    "message": "검증 성공",
    "clientId": "lzua0UoqqZIyEBz4AAAC",
    "requestId": "1763894591687_lzua0UoqqZIyEBz4AAAC",
    "details": {
      "verificationResult": [
        1,
        1,
        1,
        1,
        1
      ],
      "isSuccess": true,
      "duration": 79
    }
  },
  {
    "timestamp": "2025-11-23T10:43:12.188Z",
    "level": "info",
    "message": "요청 시작",
    "clientId": "lzua0UoqqZIyEBz4AAAC",
    "requestId": "1763894592188_lzua0UoqqZIyEBz4AAAC",
    "details": {
      "imageSize": 12848
    }
  },
  {
    "timestamp": "2025-11-23T10:43:12.269Z",
    "level": "info",
    "message": "검증 성공",
    "clientId": "lzua0UoqqZIyEBz4AAAC",
    "requestId": "1763894592188_lzua0UoqqZIyEBz4AAAC",
    "details": {
      "verificationResult": [
        1,
        1,
        1,
        1,
        1
      ],
      "isSuccess": true,
      "duration": 81
    }
  },
  {
    "timestamp": "2025-11-23T10:43:12.690Z",
    "level": "info",
    "message": "요청 시작",
    "clientId": "lzua0UoqqZIyEBz4AAAC",
    "requestId": "1763894592690_lzua0UoqqZIyEBz4AAAC",
    "details": {
      "imageSize": 13020
    }
  },
  {
    "timestamp": "2025-11-23T10:43:12.762Z",
    "level": "info",
    "message": "검증 성공",
    "clientId": "lzua0UoqqZIyEBz4AAAC",
    "requestId": "1763894592690_lzua0UoqqZIyEBz4AAAC",
    "details": {
      "verificationResult": [
        1,
        1,
        1,
        1,
        1
      ],
      "isSuccess": true,
      "duration": 72
    }
  },
  {
    "timestamp": "2025-11-23T10:43:13.189Z",
    "level": "info",
    "message": "요청 시작",
    "clientId": "lzua0UoqqZIyEBz4AAAC",
    "requestId": "1763894593189_lzua0UoqqZIyEBz4AAAC",
    "details": {
      "imageSize": 13436
    }
  },
  {
    "timestamp": "2025-11-23T10:43:13.268Z",
    "level": "info",
    "message": "검증 성공",
    "clientId": "lzua0UoqqZIyEBz4AAAC",
    "requestId": "1763894593189_lzua0UoqqZIyEBz4AAAC",
    "details": {
      "verificationResult": [
        1,
        1,
        1,
        1,
        1
      ],
      "isSuccess": true,
      "duration": 79
    }
  },
  {
    "timestamp": "2025-11-23T10:43:13.686Z",
    "level": "info",
    "message": "요청 시작",
    "clientId": "lzua0UoqqZIyEBz4AAAC",
    "requestId": "1763894593686_lzua0UoqqZIyEBz4AAAC",
    "details": {
      "imageSize": 13660
    }
  },
  {
    "timestamp": "2025-11-23T10:43:13.764Z",
    "level": "info",
    "message": "검증 성공",
    "clientId": "lzua0UoqqZIyEBz4AAAC",
    "requestId": "1763894593686_lzua0UoqqZIyEBz4AAAC",
    "details": {
      "verificationResult": [
        1,
        1,
        1,
        1,
        1
      ],
      "isSuccess": true,
      "duration": 77
    }
  },
  {
    "timestamp": "2025-11-23T10:43:14.192Z",
    "level": "info",
    "message": "요청 시작",
    "clientId": "lzua0UoqqZIyEBz4AAAC",
    "requestId": "1763894594192_lzua0UoqqZIyEBz4AAAC",
    "details": {
      "imageSize": 13776
    }
  },
  {
    "timestamp": "2025-11-23T10:43:14.270Z",
    "level": "info",
    "message": "검증 성공",
    "clientId": "lzua0UoqqZIyEBz4AAAC",
    "requestId": "1763894594192_lzua0UoqqZIyEBz4AAAC",
    "details": {
      "verificationResult": [
        1,
        1,
        1,
        1,
        1
      ],
      "isSuccess": true,
      "duration": 78
    }
  }
]